{
    "extra_params": {
        "M0": {
            "seed": 1
        },
        "M1": {
            "seed": 2
        },
        "M2": {
            "seed": 3
        },
        "M3": {
            "seed": 4
        },
        "M4": {
            "seed": 5
        },
        "M5": {
            "seed": 6
        },
        "M6": {
            "seed": 7
        },
        "M7": {
            "seed": 8
        },
        "M8": {
            "seed": 9
        },
        "M9": {
            "seed": 10
        }
    },
    "models": [
        "M0",
        "M1",
        "M2",
        "M3",
        "M4",
        "M5",
        "M6",
        "M7",
        "M8",
        "M9"
    ],
    "models_params_file": "model_params_super_basal.json",
    "morph_path": "../scripts/extract_morphologies/selected_morphologies/",
    "mtypes_sort": "super_mtypes",
    "n_cpu": 10,
    "n_morphs_max": null,
    "n_mtypes_max": 60,
    "neurite_types": [
        "basal"
    ],
    "new_morph_path": "../scripts/diameter-checks/new_morphologies_super_basal/",
    "plot": false
}